{
  "user": [
    {
      "userId": "102227633035821763864",
      "email": "wolfye0611@gmail.com",
      "userName": "긴고랑",
      "id": 1
    },
    {
      "userId": "102227633035821763864",
      "email": "wolfye0611@gmail.com",
      "userName": "긴고랑",
      "id": 2
    },
    {
      "userId": "102227633035821763864",
      "email": "wolfye0611@gmail.com",
      "userName": "긴고랑",
      "id": 3
    },
    {
      "userId": "102227633035821763864",
      "email": "wolfye0611@gmail.com",
      "userName": "긴고랑",
      "id": 4
    },
    {
      "userId": "102227633035821763864",
      "email": "wolfye0611@gmail.com",
      "userName": "긴고랑",
      "id": 5
    },
    {
      "userId": "102227633035821763864",
      "email": "wolfye0611@gmail.com",
      "userName": "긴고랑",
      "id": 6
    },
    {
      "userId": "102227633035821763864",
      "email": "wolfye0611@gmail.com",
      "userName": "긴고랑",
      "id": 7
    },
    {
      "userId": "102227633035821763864",
      "email": "wolfye0611@gmail.com",
      "userName": "긴고랑",
      "id": 8
    },
    {
      "userId": "102227633035821763864",
      "email": "wolfye0611@gmail.com",
      "userName": "긴고랑",
      "id": 9
    },
    {
      "userId": "102227633035821763864",
      "email": "wolfye0611@gmail.com",
      "userName": "긴고랑",
      "id": 10
    },
    {
      "userId": "102227633035821763864",
      "email": "wolfye0611@gmail.com",
      "userName": "긴고랑",
      "id": 11
    },
    {
      "userId": "102227633035821763864",
      "email": "wolfye0611@gmail.com",
      "userName": "긴고랑",
      "id": 12
    }
  ],
  "world": [
    {
      "title": "음식",
      "list": [
        {
          "id": "2496c5dd-091d-45aa-835c-538c298ab9a7",
          "candidate": "ㅇ",
          "roundWin": 5,
          "roundLose": 3,
          "champion": 1
        },
        {
          "id": "c3ae5f0f-cabe-402e-83d5-74af0dd5e24e",
          "candidate": "ㅍ",
          "roundWin": 7,
          "roundLose": 3,
          "champion": 1
        },
        {
          "id": "dc76d165-8653-4f13-9ee8-e59859f8c2c6",
          "candidate": "ㅜ",
          "roundWin": 2,
          "roundLose": 4,
          "champion": 0
        },
        {
          "id": "53826aa6-2812-400d-a181-b93bc6f26474",
          "candidate": "ㄹ",
          "roundWin": 2,
          "roundLose": 4,
          "champion": 0
        },
        {
          "id": "1e845234-05a1-480a-8c45-cfb46bd433a4",
          "candidate": "ㅠ",
          "roundWin": 4,
          "roundLose": 4,
          "champion": 0
        },
        {
          "id": "cee5de52-d195-46a9-ac50-fa4f278c77bf",
          "candidate": "ㅊ",
          "roundWin": 3,
          "roundLose": 4,
          "champion": 0
        },
        {
          "id": "38825384-be2c-4f86-b5f1-4135b3976b82",
          "candidate": "ㅓ",
          "roundWin": 1,
          "roundLose": 4,
          "champion": 0
        },
        {
          "id": "61013b50-e756-4647-9889-6338c8afca70",
          "candidate": "ㅊ",
          "roundWin": 5,
          "roundLose": 4,
          "champion": 0
        },
        {
          "id": "16a1db82-14cf-426a-ac36-7c99df87ce52",
          "candidate": "ㅗ",
          "roundWin": 7,
          "roundLose": 3,
          "champion": 1
        },
        {
          "id": "0ff165c0-2aed-4277-9281-720f47e22818",
          "candidate": "ㅓ",
          "roundWin": 2,
          "roundLose": 4,
          "champion": 0
        },
        {
          "id": "146eeb8f-5204-4e11-b993-3057f26cf7bf",
          "candidate": "ㄹ",
          "roundWin": 6,
          "roundLose": 4,
          "champion": 0
        },
        {
          "id": "eaa8c9bf-6b67-48a7-923b-298a15f61ed5",
          "candidate": "ㄱ",
          "roundWin": 1,
          "roundLose": 4,
          "champion": 0
        },
        {
          "id": "14c4d872-7b7c-442e-ab53-316d0fbf62b7",
          "candidate": "ㅍ",
          "roundWin": 2,
          "roundLose": 4,
          "champion": 0
        },
        {
          "id": "cadd8be3-202e-4498-8bd4-4b56cdd52f8b",
          "candidate": "ㅎ",
          "roundWin": 0,
          "roundLose": 4,
          "champion": 0
        },
        {
          "id": "1583c008-06e9-454d-bf63-07c04be02f79",
          "candidate": "ㅗ",
          "roundWin": 7,
          "roundLose": 4,
          "champion": 0
        },
        {
          "id": "51953afb-1d5f-4b5a-970c-511d182e9023",
          "candidate": "ㅍㅊ",
          "roundWin": 6,
          "roundLose": 3,
          "champion": 1
        }
      ],
      "id": "1c2d0629-3919-40dd-a22b-fc739594340b",
      "count": 4,
      "createdAt": 1646650879768,
      "comments": [],
      "creatorId": "102266349003310668092"
    },
    {
      "title": "자자",
      "list": [
        {
          "id": "67fb761f-18cd-4b32-9f8b-083b7d8e42a1",
          "candidate": "ㅓ",
          "roundWin": 5,
          "roundLose": 3,
          "champion": 1
        },
        {
          "id": "6e5de881-2733-4728-be0e-811fcde5b7ac",
          "candidate": "ㅓ",
          "roundWin": 1,
          "roundLose": 4,
          "champion": 0
        },
        {
          "id": "56a6b285-efa8-45fb-90a6-a4d1b8635605",
          "candidate": "ㅓ",
          "roundWin": 5,
          "roundLose": 3,
          "champion": 1
        },
        {
          "id": "ef06f774-8d2b-4e6a-907f-6ce8052cf07a",
          "candidate": "ㅓㅓ",
          "roundWin": 3,
          "roundLose": 4,
          "champion": 0
        },
        {
          "id": "89e648a2-772a-423d-aa18-ccfe73d651a4",
          "candidate": "ㅓ",
          "roundWin": 7,
          "roundLose": 4,
          "champion": 0
        },
        {
          "id": "81760886-3d9f-4d7f-a1f5-b7d9943e7a3d",
          "candidate": "ㅓ",
          "roundWin": 5,
          "roundLose": 3,
          "champion": 1
        },
        {
          "id": "143da4a5-b1cc-483e-a82d-bc6159ce8dc9",
          "candidate": "ㅓ",
          "roundWin": 2,
          "roundLose": 4,
          "champion": 0
        },
        {
          "id": "8fdc577b-159e-4590-bca9-fde2cd04beed",
          "candidate": "ㅓ",
          "roundWin": 3,
          "roundLose": 4,
          "champion": 0
        },
        {
          "id": "942344e3-7e6c-45fd-befc-0a492be688ea",
          "candidate": "ㅓ",
          "roundWin": 8,
          "roundLose": 3,
          "champion": 1
        },
        {
          "id": "3dc36c2f-da18-40b2-b26e-935ce073f43a",
          "candidate": "ㅓ",
          "roundWin": 5,
          "roundLose": 4,
          "champion": 0
        },
        {
          "id": "0e2b52c6-60d6-4e2c-bdd9-0fda5286a4e1",
          "candidate": "ㅓ",
          "roundWin": 1,
          "roundLose": 4,
          "champion": 0
        },
        {
          "id": "d82cb952-5045-4d87-98e8-efb13c018fee",
          "candidate": "ㅓ",
          "roundWin": 4,
          "roundLose": 4,
          "champion": 0
        },
        {
          "id": "9fba82d5-8b60-4764-9f64-aabdfe017f86",
          "candidate": "ㅓ",
          "roundWin": 4,
          "roundLose": 4,
          "champion": 0
        },
        {
          "id": "d7c39bb1-6d23-4e66-91ee-99964fc4d75c",
          "candidate": "ㅓ",
          "roundWin": 2,
          "roundLose": 4,
          "champion": 0
        },
        {
          "id": "7c39fd2b-6b9b-4bf8-ba7d-e0f1e0048afc",
          "candidate": "ㅓ",
          "roundWin": 3,
          "roundLose": 4,
          "champion": 0
        },
        {
          "id": "d39b3696-a7f3-4266-9719-478c235a4c17",
          "candidate": "ㅓ",
          "roundWin": 2,
          "roundLose": 4,
          "champion": 0
        }
      ],
      "id": "e72a0815-e2e8-46d4-aff3-83b180251479",
      "count": 4,
      "createdAt": 1646657171603,
      "comments": [],
      "creatorId": "102266349003310668092"
    },
    {
      "title": "차",
      "list": [
        {
          "id": "effa415e-c3d2-4e18-b5c6-169da5a9794f",
          "candidate": "ㅏ",
          "roundWin": 0,
          "roundLose": 0,
          "champion": 0
        },
        {
          "id": "de4f8960-7acd-4e12-a6fe-c8f41164b3a5",
          "candidate": "ㅏ",
          "roundWin": 0,
          "roundLose": 0,
          "champion": 0
        },
        {
          "id": "af809ba6-1a14-4dcb-92a7-32fa0b15f8ad",
          "candidate": "ㅏ",
          "roundWin": 0,
          "roundLose": 0,
          "champion": 0
        },
        {
          "id": "1ec0b8df-6dbb-460f-9875-3efe2a7b2cbe",
          "candidate": "ㅏ",
          "roundWin": 0,
          "roundLose": 0,
          "champion": 0
        },
        {
          "id": "4071772c-3e9a-4939-9088-4cdfda2f244a",
          "candidate": "ㅏ",
          "roundWin": 0,
          "roundLose": 0,
          "champion": 0
        },
        {
          "id": "b81e5d9f-0c00-4f47-a9b3-543f3b3fb7ec",
          "candidate": "ㅏ",
          "roundWin": 0,
          "roundLose": 0,
          "champion": 0
        },
        {
          "id": "d527c6c7-0693-41f6-b8ca-87d70d46887b",
          "candidate": "ㅏ",
          "roundWin": 0,
          "roundLose": 0,
          "champion": 0
        },
        {
          "id": "463a1a76-4669-4ea9-9950-bb938fdf86b6",
          "candidate": "ㅏ",
          "roundWin": 0,
          "roundLose": 0,
          "champion": 0
        },
        {
          "id": "b80893f1-d989-4b68-8411-6a5cc3cb5afe",
          "candidate": "ㅏ",
          "roundWin": 0,
          "roundLose": 0,
          "champion": 0
        },
        {
          "id": "90eec967-bc74-4e08-82ce-416c5aeef9bd",
          "candidate": "ㅏ",
          "roundWin": 0,
          "roundLose": 0,
          "champion": 0
        },
        {
          "id": "f0cce5e9-c5ef-4892-9f20-c6da93f603af",
          "candidate": "ㅏ",
          "roundWin": 0,
          "roundLose": 0,
          "champion": 0
        },
        {
          "id": "1e22a49a-c73d-43a2-a020-efffde8f6d3e",
          "candidate": "ㅏ",
          "roundWin": 0,
          "roundLose": 0,
          "champion": 0
        },
        {
          "id": "900f129b-d26c-48fa-a7aa-b1dc741faceb",
          "candidate": "ㅏ",
          "roundWin": 0,
          "roundLose": 0,
          "champion": 0
        },
        {
          "id": "0e0ec994-f1b2-4c54-b3e2-bf8d2dcf52f2",
          "candidate": "ㅏ",
          "roundWin": 0,
          "roundLose": 0,
          "champion": 0
        },
        {
          "id": "64d4d9f9-92b4-4416-b10b-a15927a4314f",
          "candidate": "ㅏ",
          "roundWin": 0,
          "roundLose": 0,
          "champion": 0
        },
        {
          "id": "a56fde3a-f741-482c-bbe2-2b62537ce359",
          "candidate": "ㅏ",
          "roundWin": 0,
          "roundLose": 0,
          "champion": 0
        }
      ],
      "id": "137020c9-ad12-4971-b04c-659d492c7106",
      "count": 0,
      "createdAt": 1646657281617,
      "comments": [],
      "creatorId": "102266349003310668092"
    }
  ]
}